dotnet/PyDotnet.cp310-win_amd64.pyd
dotnet/__init__.py
dotnet/asmresolve.py
dotnet/basics.py
dotnet/boost_python310-vc143-mt-x64-1_84.dll
dotnet/boost_python312-vc143-mt-1_84.dll
dotnet/boost_python312-vc143-mt-a64-1_84.dll
dotnet/boost_python312-vc143-mt-x64-1_84.dll
dotnet/classhelp.py
dotnet/commontypes.py
dotnet/extensionmethod.py
dotnet/genericmethod.py
dotnet/moduleloader.py
dotnet/overrides.py
dotnet/private.py
dotnet/proxytypes.py
dotnet/seamless.py
dotnet/version.py
dotnet/test/__init__.py
dotnet/test/test_dotnet.py
dotnet-1.5.1.dist-info/LICENSE
dotnet-1.5.1.dist-info/METADATA
dotnet-1.5.1.dist-info/WHEEL
dotnet-1.5.1.dist-info/top_level.txt
dotnet-1.5.1.dist-info/RECORD
